<?xml version="1.0" encoding="UTF-8" standalone="no"?><Widgets><Widget name="window_main"><Components><Component class="cn.liutils.cgui.gui.component.Transform"><enabled>true</enabled><scale>1.0</scale><height>186.5</height><alignHeight>CENTER</alignHeight><doesDraw>true</doesDraw><width>175.5</width><alignWidth>CENTER</alignWidth><canEdit>true</canEdit><doesListenKey>true</doesListenKey><y>0.0</y><x>0.0</x></Component><Component class="cn.liutils.cgui.gui.component.DrawTexture"><enabled>true</enabled><color>-1</color><texture>academy:textures/guis/window_node.png</texture><canEdit>true</canEdit></Component></Components><Widget name="text_nodename"><Components><Component class="cn.liutils.cgui.gui.component.Transform"><enabled>true</enabled><scale>1.0</scale><height>10.0</height><alignHeight>TOP</alignHeight><doesDraw>true</doesDraw><width>50.0</width><alignWidth>CENTER</alignWidth><canEdit>true</canEdit><doesListenKey>true</doesListenKey><y>12.0</y><x>0.0</x></Component><Component class="cn.liutils.cgui.gui.component.TextBox"><content>loading...</content><enabled>true</enabled><allowEdit>true</allowEdit><widthAlign>CENTER</widthAlign><color>16777215</color><doesEcho>false</doesEcho><heightAlign>BOTTOM</heightAlign><canEdit>false</canEdit><size>10.0</size><localized>false</localized></Component></Components></Widget><Widget name="mark_input"><Components><Component class="cn.liutils.cgui.gui.component.Transform"><enabled>true</enabled><scale>1.0</scale><height>10.0</height><alignHeight>TOP</alignHeight><doesDraw>true</doesDraw><width>6.0</width><alignWidth>LEFT</alignWidth><canEdit>true</canEdit><doesListenKey>true</doesListenKey><y>60.0</y><x>39.0</x></Component><Component class="cn.liutils.cgui.gui.component.DrawTexture"><enabled>true</enabled><color>-1</color><texture>academy:textures/guis/mark/mark_arc.png</texture><canEdit>true</canEdit></Component></Components></Widget><Widget name="text_maxload"><Components><Component class="cn.liutils.cgui.gui.component.Transform"><enabled>true</enabled><scale>1.0</scale><height>10.0</height><alignHeight>CENTER</alignHeight><doesDraw>true</doesDraw><width>60.0</width><alignWidth>CENTER</alignWidth><canEdit>true</canEdit><doesListenKey>true</doesListenKey><y>-5.0</y><x>0.0</x></Component><Component class="cn.liutils.cgui.gui.component.TextBox"><content>MAX LOAD:5/7</content><enabled>true</enabled><allowEdit>true</allowEdit><widthAlign>CENTER</widthAlign><color>16777215</color><doesEcho>false</doesEcho><heightAlign>BOTTOM</heightAlign><canEdit>true</canEdit><size>10.0</size><localized>false</localized></Component></Components></Widget><Widget name="progress_node"><Components><Component class="cn.liutils.cgui.gui.component.Transform"><enabled>true</enabled><scale>1.0</scale><height>43.0</height><alignHeight>TOP</alignHeight><doesDraw>true</doesDraw><width>26.5</width><alignWidth>LEFT</alignWidth><canEdit>true</canEdit><doesListenKey>true</doesListenKey><y>31.0</y><x>74.0</x></Component><Component class="cn.liutils.cgui.gui.component.ProgressBar"><progress>0.8738068220290431</progress><enabled>true</enabled><maxFluctSpeed>0.8</maxFluctSpeed><color>-1</color><dir>UP</dir><maxDelta>0.03</maxDelta><texture>academy:textures/guis/progress/progress_node.png</texture><illustrating>false</illustrating><canEdit>true</canEdit><fluctRegion>0.01</fluctRegion></Component></Components></Widget><Widget name="button_ssid"><Components><Component class="cn.liutils.cgui.gui.component.Transform"><enabled>true</enabled><scale>0.39</scale><height>50.0</height><alignHeight>TOP</alignHeight><doesDraw>true</doesDraw><width>50.0</width><alignWidth>LEFT</alignWidth><canEdit>true</canEdit><doesListenKey>true</doesListenKey><y>40.0</y><x>83.0</x></Component><Component class="cn.liutils.cgui.gui.component.DrawTexture"><enabled>true</enabled><color>-1</color><texture>academy:textures/guis/button/button_wifi.png</texture><canEdit>true</canEdit></Component></Components></Widget><Widget name="mark_output"><Components><Component class="cn.liutils.cgui.gui.component.Transform"><enabled>true</enabled><scale>1.0</scale><height>10.0</height><alignHeight>TOP</alignHeight><doesDraw>true</doesDraw><width>6.0</width><alignWidth>LEFT</alignWidth><canEdit>true</canEdit><doesListenKey>true</doesListenKey><y>47.0</y><x>111.0</x></Component><Component class="cn.liutils.cgui.gui.component.DrawTexture"><enabled>true</enabled><color>-1</color><texture>academy:textures/guis/mark/mark_arc.png</texture><canEdit>true</canEdit></Component></Components></Widget><Widget name="mark_net"><Components><Component class="cn.liutils.cgui.gui.component.Transform"><enabled>true</enabled><scale>1.0</scale><height>10.0</height><alignHeight>TOP</alignHeight><doesDraw>true</doesDraw><width>6.0</width><alignWidth>LEFT</alignWidth><canEdit>true</canEdit><doesListenKey>true</doesListenKey><y>34.0</y><x>39.0</x></Component><Component class="cn.liutils.cgui.gui.component.DrawTexture"><enabled>true</enabled><color>-1</color><texture>academy:textures/guis/mark/mark_arc.png</texture><canEdit>true</canEdit></Component></Components></Widget></Widget><Widget name="window_check"><Components><Component class="cn.liutils.cgui.gui.component.Transform"><enabled>true</enabled><scale>1.0</scale><height>55.0</height><alignHeight>CENTER</alignHeight><doesDraw>true</doesDraw><width>104.5</width><alignWidth>CENTER</alignWidth><canEdit>true</canEdit><doesListenKey>true</doesListenKey><y>-10.0</y><x>0.0</x></Component><Component class="cn.liutils.cgui.gui.component.DrawTexture"><enabled>true</enabled><color>-1</color><texture>academy:textures/guis/window_check.png</texture><canEdit>true</canEdit></Component></Components><Widget name="button_close"><Components><Component class="cn.liutils.cgui.gui.component.Transform"><enabled>true</enabled><scale>1.0</scale><height>10.0</height><alignHeight>TOP</alignHeight><doesDraw>true</doesDraw><width>10.0</width><alignWidth>RIGHT</alignWidth><canEdit>true</canEdit><doesListenKey>true</doesListenKey><y>2.0</y><x>-2.0</x></Component><Component class="cn.liutils.cgui.gui.component.DrawTexture"><enabled>true</enabled><color>-1</color><texture>academy:textures/guis/button/button_close.png</texture><canEdit>true</canEdit></Component></Components></Widget><Widget name="text_pw"><Components><Component class="cn.liutils.cgui.gui.component.Transform"><enabled>true</enabled><scale>1.0</scale><height>10.0</height><alignHeight>TOP</alignHeight><doesDraw>true</doesDraw><width>70.0</width><alignWidth>LEFT</alignWidth><canEdit>true</canEdit><doesListenKey>true</doesListenKey><y>20.0</y><x>17.0</x></Component><Component class="cn.liutils.cgui.gui.component.TextBox"><content/><enabled>true</enabled><allowEdit>true</allowEdit><widthAlign>CENTER</widthAlign><color>16777215</color><doesEcho>false</doesEcho><heightAlign>BOTTOM</heightAlign><canEdit>true</canEdit><size>9.0</size><localized>false</localized></Component></Components></Widget><Widget name="mark_state2"><Components><Component class="cn.liutils.cgui.gui.component.Transform"><enabled>true</enabled><scale>1.0</scale><height>10.0</height><alignHeight>TOP</alignHeight><doesDraw>true</doesDraw><width>10.0</width><alignWidth>LEFT</alignWidth><canEdit>true</canEdit><doesListenKey>true</doesListenKey><y>14.0</y><x>47.5</x></Component><Component class="cn.liutils.cgui.gui.component.DrawTexture"><enabled>true</enabled><color>-1</color><texture>academy:textures/guis/mark/mark_loading.png</texture><canEdit>true</canEdit></Component></Components></Widget><Widget name="mark_state"><Components><Component class="cn.liutils.cgui.gui.component.Transform"><enabled>true</enabled><scale>1.0</scale><height>28.5</height><alignHeight>BOTTOM</alignHeight><doesDraw>true</doesDraw><width>25.5</width><alignWidth>CENTER</alignWidth><canEdit>true</canEdit><doesListenKey>true</doesListenKey><y>-22.0</y><x>0.0</x></Component><Component class="cn.liutils.cgui.gui.component.DrawTexture"><enabled>true</enabled><color>-1</color><texture>academy:textures/guis/mark/mark_test.png</texture><canEdit>true</canEdit></Component></Components></Widget><Widget name="button_yes"><Components><Component class="cn.liutils.cgui.gui.component.Transform"><enabled>true</enabled><scale>1.0</scale><height>13.0</height><alignHeight>BOTTOM</alignHeight><doesDraw>true</doesDraw><width>28.0</width><alignWidth>CENTER</alignWidth><canEdit>true</canEdit><doesListenKey>true</doesListenKey><y>-5.0</y><x>0.0</x></Component><Component class="cn.liutils.cgui.gui.component.DrawTexture"><enabled>true</enabled><color>-1</color><texture>academy:textures/guis/button/button_yes.png</texture><canEdit>true</canEdit></Component></Components></Widget><Widget name="input_pw"><Components><Component class="cn.liutils.cgui.gui.component.Transform"><enabled>true</enabled><scale>1.0</scale><height>21.5</height><alignHeight>BOTTOM</alignHeight><doesDraw>true</doesDraw><width>78.6</width><alignWidth>CENTER</alignWidth><canEdit>true</canEdit><doesListenKey>false</doesListenKey><y>-24.0</y><x>0.0</x></Component><Component class="cn.liutils.cgui.gui.component.DrawTexture"><enabled>true</enabled><color>-1</color><texture>academy:textures/guis/input/input_password.png</texture><canEdit>true</canEdit></Component></Components></Widget></Widget><Widget name="window_ssidselect"><Components><Component class="cn.liutils.cgui.gui.component.Transform"><enabled>true</enabled><scale>1.0</scale><height>161.5</height><alignHeight>CENTER</alignHeight><doesDraw>true</doesDraw><width>136.5</width><alignWidth>CENTER</alignWidth><canEdit>true</canEdit><doesListenKey>true</doesListenKey><y>-12.0</y><x>0.0</x></Component><Component class="cn.liutils.cgui.gui.component.DrawTexture"><enabled>true</enabled><color>-1</color><texture>academy:textures/guis/window_ssidSelect.png</texture><canEdit>true</canEdit></Component></Components><Widget name="button_close"><Components><Component class="cn.liutils.cgui.gui.component.Transform"><enabled>true</enabled><scale>1.0</scale><height>10.0</height><alignHeight>TOP</alignHeight><doesDraw>true</doesDraw><width>10.0</width><alignWidth>RIGHT</alignWidth><canEdit>true</canEdit><doesListenKey>true</doesListenKey><y>2.0</y><x>-2.0</x></Component><Component class="cn.liutils.cgui.gui.component.DrawTexture"><enabled>true</enabled><color>-1</color><texture>academy:textures/guis/button/button_close.png</texture><canEdit>true</canEdit></Component></Components></Widget><Widget name="list"><Components><Component class="cn.liutils.cgui.gui.component.Transform"><enabled>true</enabled><scale>1.0</scale><height>115.0</height><alignHeight>TOP</alignHeight><doesDraw>true</doesDraw><width>102.0</width><alignWidth>LEFT</alignWidth><canEdit>true</canEdit><doesListenKey>true</doesListenKey><y>43.5</y><x>12.0</x></Component></Components></Widget><Widget name="text_currentnet2"><Components><Component class="cn.liutils.cgui.gui.component.Transform"><enabled>true</enabled><scale>1.0</scale><height>12.0</height><alignHeight>TOP</alignHeight><doesDraw>true</doesDraw><width>102.0</width><alignWidth>LEFT</alignWidth><canEdit>true</canEdit><doesListenKey>true</doesListenKey><y>19.0</y><x>33.0</x></Component><Component class="cn.liutils.cgui.gui.component.TextBox"><content>MEOW</content><enabled>true</enabled><allowEdit>false</allowEdit><widthAlign>CENTER</widthAlign><color>16777215</color><doesEcho>false</doesEcho><heightAlign>BOTTOM</heightAlign><canEdit>true</canEdit><size>10.0</size><localized>false</localized></Component></Components></Widget><Widget name="button_slide"><Components><Component class="cn.liutils.cgui.gui.component.Transform"><enabled>true</enabled><scale>1.0</scale><height>20.0</height><alignHeight>TOP</alignHeight><doesDraw>true</doesDraw><width>11.0</width><alignWidth>LEFT</alignWidth><canEdit>true</canEdit><doesListenKey>true</doesListenKey><y>39.0</y><x>114.0</x></Component><Component class="cn.liutils.cgui.gui.component.DrawTexture"><enabled>true</enabled><color>-1</color><texture>academy:textures/guis/button/button_slide_normal.png</texture><canEdit>true</canEdit></Component><Component class="cn.liutils.cgui.gui.component.VerticalDragBar"><enabled>true</enabled><y0>39.0</y0><y1>137.0</y1><canEdit>true</canEdit></Component></Components></Widget><Widget name="ssid_template"><Components><Component class="cn.liutils.cgui.gui.component.Transform"><enabled>true</enabled><scale>1.0</scale><height>13.0</height><alignHeight>TOP</alignHeight><doesDraw>false</doesDraw><width>102.0</width><alignWidth>LEFT</alignWidth><canEdit>true</canEdit><doesListenKey>true</doesListenKey><y>44.0</y><x>12.0</x></Component><Component class="cn.liutils.cgui.gui.component.TextBox"><content>SomeSSID</content><enabled>true</enabled><allowEdit>false</allowEdit><widthAlign>LEFT</widthAlign><color>16777215</color><doesEcho>false</doesEcho><heightAlign>BOTTOM</heightAlign><canEdit>true</canEdit><size>10.0</size><localized>false</localized></Component><Component class="cn.liutils.cgui.gui.component.Tint"><enabled>true</enabled><canEdit>true</canEdit><idleColor>0</idleColor><hoverColor>1728053247</hoverColor></Component></Components></Widget><Widget name="text_currentnet"><Components><Component class="cn.liutils.cgui.gui.component.Transform"><enabled>true</enabled><scale>1.0</scale><height>12.0</height><alignHeight>TOP</alignHeight><doesDraw>true</doesDraw><width>60.0</width><alignWidth>LEFT</alignWidth><canEdit>true</canEdit><doesListenKey>true</doesListenKey><y>6.0</y><x>33.0</x></Component><Component class="cn.liutils.cgui.gui.component.TextBox"><content>CURRENT NET:</content><enabled>true</enabled><allowEdit>false</allowEdit><widthAlign>LEFT</widthAlign><color>16777215</color><doesEcho>false</doesEcho><heightAlign>BOTTOM</heightAlign><canEdit>true</canEdit><size>10.0</size><localized>false</localized></Component></Components></Widget></Widget></Widgets>