<?xml version="1.0" encoding="UTF-8" standalone="no"?><Root><Widget name="main"><Component class="cn.lambdalib2.cgui.component.Transform"><width>144.0</width><height>203.0</height><x>94.0</x><y>104.0</y><pivotX>0.0</pivotX><pivotY>0.0</pivotY><scale>0.5</scale><doesDraw>true</doesDraw><doesListenKey>true</doesListenKey><alignWidth>LEFT</alignWidth><alignHeight>TOP</alignHeight><enabled>true</enabled></Component><Component class="cn.lambdalib2.cgui.component.DrawTexture"><texture>academy:textures/guis/window_ui_resize.png</texture><color><red>255</red><green>255</green><blue>255</blue><alpha>255</alpha></color><zLevel>0.0</zLevel><writeDepth>true</writeDepth><enabled>true</enabled></Component><Widget name="header"><Component class="cn.lambdalib2.cgui.component.Transform"><width>128.0</width><height>28.0</height><x>0.0</x><y>8.0</y><pivotX>0.0</pivotX><pivotY>0.0</pivotY><scale>1.0</scale><doesDraw>true</doesDraw><doesListenKey>true</doesListenKey><alignWidth>CENTER</alignWidth><alignHeight>TOP</alignHeight><enabled>true</enabled></Component><Component class="cn.lambdalib2.cgui.component.TextBox"><content>ac.gui.uiedit.elements</content><font>AC_Normal</font><option><fontSize>18.0</fontSize><align>LEFT</align><color><red>255</red><green>255</green><blue>255</blue><alpha>187</alpha></color></option><heightAlign>CENTER</heightAlign><localized>true</localized><allowEdit>false</allowEdit><emit>true</emit><doesEcho>false</doesEcho><echoChar>*</echoChar><zLevel>0.0</zLevel><xOffset>5.0</xOffset><yOffset>0.0</yOffset><enabled>true</enabled></Component></Widget><Widget name="body"><Component class="cn.lambdalib2.cgui.component.Transform"><width>128.0</width><height>160.0</height><x>0.0</x><y>36.0</y><pivotX>0.0</pivotX><pivotY>0.0</pivotY><scale>1.0</scale><doesDraw>true</doesDraw><doesListenKey>true</doesListenKey><alignWidth>CENTER</alignWidth><alignHeight>TOP</alignHeight><enabled>true</enabled></Component><Widget name="template"><Component class="cn.lambdalib2.cgui.component.Transform"><width>128.0</width><height>24.0</height><x>0.0</x><y>0.0</y><pivotX>0.0</pivotX><pivotY>0.0</pivotY><scale>1.0</scale><doesDraw>false</doesDraw><doesListenKey>true</doesListenKey><alignWidth>CENTER</alignWidth><alignHeight>TOP</alignHeight><enabled>true</enabled></Component><Component class="cn.lambdalib2.cgui.component.Tint"><idleColor><red>255</red><green>255</green><blue>255</blue><alpha>25</alpha></idleColor><hoverColor><red>255</red><green>255</green><blue>255</blue><alpha>127</alpha></hoverColor><affectTexture>false</affectTexture><zLevel>0.0</zLevel><enabled>true</enabled></Component><Component class="cn.lambdalib2.cgui.component.TextBox"><content>CP Indicator</content><font>AC_Normal</font><option><fontSize>18.0</fontSize><align>LEFT</align><color><red>255</red><green>255</green><blue>255</blue><alpha>255</alpha></color></option><heightAlign>CENTER</heightAlign><localized>false</localized><allowEdit>false</allowEdit><emit>true</emit><doesEcho>false</doesEcho><echoChar>*</echoChar><zLevel>0.0</zLevel><xOffset>10.0</xOffset><yOffset>0.0</yOffset><enabled>true</enabled></Component></Widget></Widget></Widget><Widget name="editbox"><Component class="cn.lambdalib2.cgui.component.Transform"><width>90.0</width><height>16.0</height><x>167.0</x><y>121.0</y><pivotX>0.0</pivotX><pivotY>0.0</pivotY><scale>1.0</scale><doesDraw>true</doesDraw><doesListenKey>true</doesListenKey><alignWidth>LEFT</alignWidth><alignHeight>TOP</alignHeight><enabled>true</enabled></Component><Component class="cn.lambdalib2.cgui.component.DrawTexture"><texture isNull="true"/><color><red>34</red><green>34</green><blue>34</blue><alpha>187</alpha></color><zLevel>0.0</zLevel><writeDepth>true</writeDepth><enabled>true</enabled></Component><Component class="cn.lambdalib2.cgui.component.Outline"><color><red>255</red><green>255</green><blue>255</blue><alpha>255</alpha></color><lineWidth>2.0</lineWidth><enabled>true</enabled></Component><Widget name="text_x"><Component class="cn.lambdalib2.cgui.component.Transform"><width>10.0</width><height>10.0</height><x>2.0</x><y>3.0</y><pivotX>0.0</pivotX><pivotY>0.0</pivotY><scale>1.0</scale><doesDraw>true</doesDraw><doesListenKey>true</doesListenKey><alignWidth>LEFT</alignWidth><alignHeight>TOP</alignHeight><enabled>true</enabled></Component><Component class="cn.lambdalib2.cgui.component.TextBox"><content>X</content><font>AC_Normal</font><option><fontSize>10.0</fontSize><align>LEFT</align><color><red>255</red><green>255</green><blue>255</blue><alpha>255</alpha></color></option><heightAlign>CENTER</heightAlign><localized>false</localized><allowEdit>false</allowEdit><emit>true</emit><doesEcho>false</doesEcho><echoChar>*</echoChar><zLevel>0.0</zLevel><xOffset>0.0</xOffset><yOffset>0.0</yOffset><enabled>true</enabled></Component></Widget><Widget name="edit_x"><Component class="cn.lambdalib2.cgui.component.Transform"><width>34.0</width><height>10.0</height><x>10.0</x><y>3.0</y><pivotX>0.0</pivotX><pivotY>0.0</pivotY><scale>1.0</scale><doesDraw>true</doesDraw><doesListenKey>true</doesListenKey><alignWidth>LEFT</alignWidth><alignHeight>TOP</alignHeight><enabled>true</enabled></Component><Component class="cn.lambdalib2.cgui.component.DrawTexture"><texture isNull="true"/><color><red>51</red><green>51</green><blue>51</blue><alpha>255</alpha></color><zLevel>0.0</zLevel><writeDepth>true</writeDepth><enabled>true</enabled></Component><Component class="cn.lambdalib2.cgui.component.TextBox"><content/><font>AC_Normal</font><option><fontSize>10.0</fontSize><align>LEFT</align><color><red>255</red><green>255</green><blue>255</blue><alpha>255</alpha></color></option><heightAlign>CENTER</heightAlign><localized>false</localized><allowEdit>true</allowEdit><emit>true</emit><doesEcho>false</doesEcho><echoChar>*</echoChar><zLevel>0.0</zLevel><xOffset>0.0</xOffset><yOffset>0.0</yOffset><enabled>true</enabled></Component></Widget><Widget name="text_y"><Component class="cn.lambdalib2.cgui.component.Transform"><width>10.0</width><height>10.0</height><x>46.0</x><y>3.0</y><pivotX>0.0</pivotX><pivotY>0.0</pivotY><scale>1.0</scale><doesDraw>true</doesDraw><doesListenKey>true</doesListenKey><alignWidth>LEFT</alignWidth><alignHeight>TOP</alignHeight><enabled>true</enabled></Component><Component class="cn.lambdalib2.cgui.component.TextBox"><content>Y</content><font>AC_Normal</font><option><fontSize>10.0</fontSize><align>LEFT</align><color><red>255</red><green>255</green><blue>255</blue><alpha>255</alpha></color></option><heightAlign>CENTER</heightAlign><localized>false</localized><allowEdit>false</allowEdit><emit>true</emit><doesEcho>false</doesEcho><echoChar>*</echoChar><zLevel>0.0</zLevel><xOffset>0.0</xOffset><yOffset>0.0</yOffset><enabled>true</enabled></Component></Widget><Widget name="edit_y"><Component class="cn.lambdalib2.cgui.component.Transform"><width>34.0</width><height>10.0</height><x>53.0</x><y>3.0</y><pivotX>0.0</pivotX><pivotY>0.0</pivotY><scale>1.0</scale><doesDraw>true</doesDraw><doesListenKey>true</doesListenKey><alignWidth>LEFT</alignWidth><alignHeight>TOP</alignHeight><enabled>true</enabled></Component><Component class="cn.lambdalib2.cgui.component.DrawTexture"><texture isNull="true"/><color><red>51</red><green>51</green><blue>51</blue><alpha>255</alpha></color><zLevel>0.0</zLevel><writeDepth>true</writeDepth><enabled>true</enabled></Component><Component class="cn.lambdalib2.cgui.component.TextBox"><content/><font>AC_Normal</font><option><fontSize>10.0</fontSize><align>LEFT</align><color><red>255</red><green>255</green><blue>255</blue><alpha>255</alpha></color></option><heightAlign>CENTER</heightAlign><localized>false</localized><allowEdit>true</allowEdit><emit>true</emit><doesEcho>false</doesEcho><echoChar>*</echoChar><zLevel>0.0</zLevel><xOffset>0.0</xOffset><yOffset>0.0</yOffset><enabled>true</enabled></Component></Widget></Widget></Root>